image_text_recognition/__init__.py
image_text_recognition/evaluate.py
image_text_recognition/generate.py
image_text_recognition/image_text_recognition.py
image_text_recognition-0.1.1.dist-info/METADATA
image_text_recognition-0.1.1.dist-info/WHEEL
image_text_recognition-0.1.1.dist-info/top_level.txt
image_text_recognition-0.1.1.dist-info/RECORD
