Metadata-Version: 2.1
Name: image-text-recognition
Version: 0.1.1
Summary: A package for recognizing and evaluating text in images
Home-page: 
Author: Amit Acharya
Author-email: amitjagadeesh2004@gmail.com
Classifier: Programming Language :: Python :: 3
Classifier: License :: OSI Approved :: MIT License
Classifier: Operating System :: OS Independent
Requires-Python: >=3.6
Requires-Dist: easyocr
Requires-Dist: numpy
Requires-Dist: Pillow
Requires-Dist: opencv-python
Requires-Dist: scikit-learn
